{
  "id": "new_game",
  "name": "New Game",
  "initialPlayerState": {
    "mapId": "europe1",
    "areaId": null,
    "position": {
      "x": 0,
      "y": 0
    },
    "vehicle": "/vehicles/walking_boy.json",
    "store": {}
  },
  "tasks": [],
  "maps": {
    "europe1": {
      "mapId": "europe1",
      "mapJsonPath": "/maps/europe.json",
      "areas": {
        "ellipse_copy": {
          "display": {
            "showBackground": false
          },
          "onEnterMessage": {
            "text": "asdf"
          },
          "onExitMessage": {
            "text": "fdsa"
          }
        },
        "rect": {
          "transition": {
            "targetMapId": "france0",
            "targetMapJsonPath": "/maps/france2.json",
            "returnToMapId": "europe1",
            "returnToAreaId": "rect"
          }
        }
      }
    },
    "france0": {
      "mapId": "france0",
      "mapJsonPath": "/maps/france2.json",
      "parentMapId": "europe1",
      "parentAreaId": "rect",
      "areas": {
        "rect": {
          "onEnterMessage": {
            "text": "Paris!"
          },
          "onExitMessage": {
            "text": "Au revoir!"
          }
        }
      }
    }
  }
}
